LICENSE
MANIFEST.in
README.md
align_face.py
install.txt
main.py
requirements.txt
setup.py
Azule_Hair_Transplant.egg-info/PKG-INFO
Azule_Hair_Transplant.egg-info/SOURCES.txt
Azule_Hair_Transplant.egg-info/dependency_links.txt
Azule_Hair_Transplant.egg-info/top_level.txt
datasets/__init__.py
datasets/image_dataset.py
losses/__init__.py
losses/align_loss.py
losses/blend_loss.py
losses/embedding_loss.py
losses/vgg_loss.py
losses/lpips/__init__.py
losses/lpips/base_model.py
losses/lpips/dist_model.py
losses/lpips/networks_basic.py
losses/lpips/pretrained_networks.py
losses/masked_lpips/__init__.py
losses/masked_lpips/base_model.py
losses/masked_lpips/dist_model.py
losses/masked_lpips/networks_basic.py
losses/masked_lpips/pretrained_networks.py
losses/style/__init__.py
losses/style/custom_loss.py
losses/style/style_loss.py
losses/style/vgg_activations.py
models/Alignment.py
models/Blending.py
models/Embedding.py
models/Net.py
models/__init__.py
models/face_parsing/face_dataset.py
models/face_parsing/makeup.py
models/face_parsing/model.py
models/face_parsing/prepropess_data.py
models/face_parsing/resnet.py
models/face_parsing/transform.py
models/face_parsing/modules/__init__.py
models/face_parsing/modules/bn.py
models/face_parsing/modules/deeplab.py
models/face_parsing/modules/dense.py
models/face_parsing/modules/functions.py
models/face_parsing/modules/misc.py
models/face_parsing/modules/residual.py
models/optimizer/ClampOptimizer.py
models/optimizer/__init__.py
models/stylegan2/__init__.py
models/stylegan2/model.py
models/stylegan2/op/__init__.py
models/stylegan2/op/fused_act.py
models/stylegan2/op/upfirdn2d.py
utils/PCA_utils.py
utils/__init__.py
utils/bicubic.py
utils/data_utils.py
utils/drive.py
utils/image_utils.py
utils/model_utils.py
utils/seg_utils.py
utils/shape_predictor.py