Metadata-Version: 2.1
Name: Azule-Hair-Transplant
Version: 0.0.1
Summary: Hair Transplant
Author: arin.adil
Author-email: azule107@gmail.com
Classifier: Development Status :: 5 - Production/Stable
Classifier: Intended Audience :: Education
Classifier: Operating System :: Microsoft :: Windows :: Windows 11
Classifier: License :: OSI Approved :: MIT License
Classifier: Programming Language :: Python :: 2
License-File: LICENSE
